log_with_context/__init__.py
log_with_context/py.typed
log_with_context-0.6.0.dist-info/LICENSE
log_with_context-0.6.0.dist-info/METADATA
log_with_context-0.6.0.dist-info/WHEEL
log_with_context-0.6.0.dist-info/RECORD
