Metadata-Version: 2.1
Name: log-with-context
Version: 0.6.0
Summary: a thread-local, context-preserving Python logger
Home-page: https://github.com/neocrym/log-with-context
License: MIT
Author: Neocrym Records Inc.
Author-email: engineering@neocrym.com
Requires-Python: >=3.8,<4.0
Classifier: License :: OSI Approved :: MIT License
Classifier: Programming Language :: Python :: 3
Classifier: Programming Language :: Python :: 3.8
Classifier: Programming Language :: Python :: 3.9
Classifier: Programming Language :: Python :: 3.10
Classifier: Programming Language :: Python :: 3.11
Requires-Dist: typing-extensions (>=4.8.0,<5.0.0)
Project-URL: Repository, https://github.com/neocrym/log-with-context
